flowcraft/__init__.py
flowcraft/flowcraft.py
flowcraft/nextflow.config
flowcraft/profiles.config
flowcraft/bin/final_POST.sh
flowcraft/bin/merge_json.py
flowcraft/bin/metadata_POST.sh
flowcraft/bin/parse_fasta.py
flowcraft/bin/parse_true_coverage.py
flowcraft/bin/prepare_reports.py
flowcraft/bin/renamePE_samtoolsFASTQ.py
flowcraft/bin/report_POST.sh
flowcraft/bin/set_dotfiles.sh
flowcraft/bin/startup_POST.sh
flowcraft/generator/__init__.py
flowcraft/generator/engine.py
flowcraft/generator/error_handling.py
flowcraft/generator/footer_skeleton.py
flowcraft/generator/header_skeleton.py
flowcraft/generator/inspect.py
flowcraft/generator/pipeline_parser.py
flowcraft/generator/process.py
flowcraft/generator/process_collector.py
flowcraft/generator/process_details.py
flowcraft/generator/recipe.py
flowcraft/generator/report.py
flowcraft/generator/utils.py
flowcraft/generator/components/__init__.py
flowcraft/generator/components/alignment.py
flowcraft/generator/components/annotation.py
flowcraft/generator/components/assembly.py
flowcraft/generator/components/assembly_processing.py
flowcraft/generator/components/distance_estimation.py
flowcraft/generator/components/downloads.py
flowcraft/generator/components/mapping.py
flowcraft/generator/components/metagenomics.py
flowcraft/generator/components/mlst.py
flowcraft/generator/components/patlas_mapping.py
flowcraft/generator/components/phylogeny.py
flowcraft/generator/components/reads_quality_control.py
flowcraft/generator/components/typing.py
flowcraft/generator/recipes/__init__.py
flowcraft/generator/recipes/denim.py
flowcraft/generator/recipes/innuca.py
flowcraft/generator/recipes/plasmids.py
flowcraft/generator/templates/Helper.groovy
flowcraft/generator/templates/abricate.nf
flowcraft/generator/templates/abyss.nf
flowcraft/generator/templates/assembly_mapping.nf
flowcraft/generator/templates/bandage.nf
flowcraft/generator/templates/bcalm.nf
flowcraft-1.4.1.dist-info/METADATA
flowcraft-1.4.1.dist-info/RECORD
flowcraft-1.4.1.dist-info/WHEEL
flowcraft-1.4.1.dist-info/entry_points.txt
flowcraft-1.4.1.dist-info/top_level.txt
