Metadata-Version: 2.1
Name: flowcraft
Version: 1.4.1
Summary: A Nextflow pipeline assembler for genomics. Pick your modules. Assemble them. Run the pipeline.
Home-page: https://github.com/assemblerflow/flowcraft
Author: Diogo N Silva
Author-email: o.diogosilva@gmail.com
License: GPL3
Platform: UNKNOWN
Requires-Dist: pympler
Requires-Dist: python-dateutil
Requires-Dist: argparse
Requires-Dist: jinja2
Requires-Dist: requests
